{
    "levelNumber": 525,
    "targetScore": 0,
    "movesLeft": 42,
    "timeLeft": 0,
    "tiles": [
        [
            0,
            1,
            1,
            1,
            1,
            1,
            0
        ],
        [
            1,
            1,
            1,
            1,
            1,
            1,
            1
        ],
        [
            0,
            1,
            1,
            1,
            1,
            1,
            0
        ],
        [
            0,
            1,
            1,
            1,
            1,
            1,
            0
        ],
        [
            0,
            1,
            1,
            1,
            1,
            1,
            0
        ],
        [
            0,
            1,
            1,
            1,
            1,
            1,
            0
        ],
        [
            1,
            1,
            1,
            1,
            1,
            1,
            1
        ],
        [
            0,
            1,
            1,
            1,
            1,
            1,
            0
        ]
    ],
    "colors": [
        "candy6",
        "candy3",
        "candy1",
        "candy4",
        "candy2"
    ],
    "targetCandies": {
        "candy3": 54,
        "candy6": 54,
        "candy2": 54,
        "candy4": 54
    }
}