{
    "levelNumber": 563,
    "targetScore": 0,
    "movesLeft": 44,
    "timeLeft": 0,
    "tiles": [
        [
            1,
            1,
            1,
            1,
            1,
            1
        ],
        [
            1,
            1,
            1,
            1,
            1,
            1
        ],
        [
            1,
            1,
            1,
            1,
            1,
            1
        ],
        [
            1,
            1,
            1,
            1,
            1,
            1
        ],
        [
            1,
            1,
            1,
            1,
            1,
            1
        ],
        [
            1,
            1,
            1,
            1,
            1,
            1
        ]
    ],
    "colors": [
        "candy2",
        "candy6",
        "candy1",
        "candy3",
        "candy4"
    ],
    "targetCandies": {
        "candy6": 57,
        "candy1": 57,
        "candy3": 57,
        "candy2": 57
    }
}