{
    "levelNumber": 92,
    "targetScore": 0,
    "movesLeft": 24,
    "timeLeft": 0,
    "tiles": [
        [
            1,
            1,
            0,
            0,
            0,
            1,
            1
        ],
        [
            1,
            1,
            1,
            1,
            1,
            1,
            1
        ],
        [
            1,
            1,
            1,
            1,
            1,
            1,
            1
        ],
        [
            1,
            1,
            1,
            1,
            1,
            1,
            1
        ],
        [
            1,
            1,
            1,
            1,
            1,
            1,
            1
        ],
        [
            1,
            1,
            1,
            1,
            1,
            1,
            1
        ],
        [
            1,
            1,
            1,
            1,
            1,
            1,
            1
        ],
        [
            1,
            1,
            0,
            0,
            0,
            1,
            1
        ]
    ],
    "colors": [
        "candy4",
        "candy1",
        "candy6",
        "candy3",
        "candy2"
    ],
    "targetCandies": {
        "candy3": 18,
        "candy4": 18,
        "candy1": 18,
        "candy6": 18
    }
}